tacf/__init__.py
tacf-0.0.0.dist-info/METADATA
tacf-0.0.0.dist-info/WHEEL
tacf-0.0.0.dist-info/top_level.txt
tacf-0.0.0.dist-info/RECORD
