Metadata-Version: 2.1
Name: tacf
Version: 0.0.0
Summary: Tkinter Advaced Canvas Framework
Author-email: Xiaokang2022 <2951256653@qq.com>
Maintainer-email: Xiaokang2022 <2951256653@qq.com>
Keywords: tkinter,tkintertools,gui,ui,3d,cross-platform,themed
Classifier: Programming Language :: Python :: 3
Classifier: License :: OSI Approved :: MIT License
Classifier: Operating System :: Microsoft :: Windows
Classifier: Operating System :: POSIX :: Linux
Classifier: Operating System :: MacOS
Classifier: Intended Audience :: Developers
Classifier: Natural Language :: English
Classifier: Natural Language :: Chinese (Simplified)
Classifier: Topic :: Software Development :: Libraries :: Python Modules
Classifier: Topic :: Software Development :: Widget Sets
Classifier: Typing :: Typed
Requires-Python: >=3.10
